pytk/Geometry.py
pytk/__init__.py
pytk/_version.py
pytk/util.py
pytk/widgets.py
pytk-0.0.2.0.dist-info/LICENSE.rst
pytk-0.0.2.0.dist-info/METADATA
pytk-0.0.2.0.dist-info/WHEEL
pytk-0.0.2.0.dist-info/top_level.txt
pytk-0.0.2.0.dist-info/RECORD
