Metadata-Version: 2.1
Name: pytk
Version: 0.0.2.0
Summary: Automatic generation of user-interfaces.
Home-page: https://github.com/norok2/pytk
Author: Riccardo Metere
Author-email: rick@metere.it
License: GPLv3+
Keywords: automatic,ui,user interface,user-interface,gui,graphical user-interface,tui
Platform: UNKNOWN
Classifier: Development Status :: 3 - Alpha
Classifier: Intended Audience :: Developers
Classifier: Intended Audience :: Information Technology
Classifier: Intended Audience :: End Users/Desktop
Classifier: Intended Audience :: System Administrators
Classifier: Intended Audience :: Science/Research
Classifier: Intended Audience :: Education
Classifier: Natural Language :: English
Classifier: Topic :: Software Development
Classifier: Topic :: Software Development :: Libraries
Classifier: Topic :: Utilities
Classifier: Operating System :: POSIX
Classifier: License :: OSI Approved :: GNU General Public License v3 or later (GPLv3+)
Classifier: Programming Language :: Python
Classifier: Programming Language :: Python :: 2
Classifier: Programming Language :: Python :: 3
Requires-Dist: flyingcircus
